__init__.py
bufferreader.py
bufferreader-1.0.0.dist-info/LICENSE
bufferreader-1.0.0.dist-info/METADATA
bufferreader-1.0.0.dist-info/WHEEL
bufferreader-1.0.0.dist-info/top_level.txt
bufferreader-1.0.0.dist-info/RECORD
