Metadata-Version: 2.1
Name: bufferreader
Version: 1.0.0
Summary: Text buffer with a pointer to line number and character number.
Author-email: Vladimir Jovanovic <vladimirjo@protonmail.com>
License: MIT
Keywords: buffer,text,string,parse
Classifier: Programming Language :: Python :: 3
Requires-Python: >=3.10
License-File: LICENSE
Provides-Extra: build
Requires-Dist: build; extra == "build"
Requires-Dist: setuptools; extra == "build"
Requires-Dist: twine; extra == "build"
Provides-Extra: check
Requires-Dist: ruff; extra == "check"
Requires-Dist: mypy; extra == "check"
Provides-Extra: dev
Requires-Dist: bufferreader[build,check,test]; extra == "dev"
Provides-Extra: test
Requires-Dist: pytest; extra == "test"
Requires-Dist: pytest-cov; extra == "test"
